[
    {
        "id": "fHlQRf",
        "title": "Quiz sur les chats",
        "description": "Un quiz sur les chats",
        "duration": 20,
        "lastModification": "2023-11-29   4:55:29 AM",
        "isVisible": true,
        "questions": [
            {
                "text": "Êtes-vous un fan des chats?",
                "points": 10,
                "type": "QCM",
                "choices": [
                    {
                        "text": "Oui",
                        "isCorrect": true
                    },
                    {
                        "text": "Évidemment",
                        "isCorrect": true
                    },
                    {
                        "text": "Absolument",
                        "isCorrect": true
                    },
                    {
                        "text": "Non",
                        "isCorrect": false
                    }
                ]
            },
            {
                "text": "Que signifie un chat qui vous montre son ventre?",
                "points": 10,
                "type": "QRL"
            },
            {
                "text": "Où pouvez-vous faire du bénévolat pour interagir avec des chats?",
                "points": 40,
                "type": "QCM",
                "choices": [
                    {
                        "text": "SPCA",
                        "isCorrect": true
                    },
                    {
                        "text": "Réseau Secours Animal",
                        "isCorrect": true
                    },
                    {
                        "text": "Tropicazoo ",
                        "isCorrect": false
                    },
                    {
                        "text": "Chico du Plateau Mont-Royal ",
                        "isCorrect": false
                    }
                ]
            },
            {
                "text": "Que pensez-vous du film Puss in Boots: The Last Wish? ",
                "points": 10,
                "type": "QRL"
            }
        ]
    },
    {
        "id": "c7D8Pu",
        "title": "Testing Quiz",
        "description": "Quiz for testing",
        "duration": 15,
        "lastModification": "2023-11-29   4:11:05 AM",
        "isVisible": true,
        "questions": [
            {
                "text": "First question",
                "points": 20,
                "type": "QRL"
            },
            {
                "text": "Last question",
                "points": 10,
                "type": "QCM",
                "choices": [
                    {
                        "text": "Good ",
                        "isCorrect": true
                    },
                    {
                        "text": "Bad",
                        "isCorrect": false
                    },
                    {
                        "text": "Bad.",
                        "isCorrect": false
                    },
                    {
                        "text": "Bad..",
                        "isCorrect": false
                    }
                ]
            }
        ]
    },
    {
        "id": "iJzvs3",
        "title": "QRL tests",
        "description": "QRL tests",
        "duration": 30,
        "lastModification": "2023-11-29   5:14:53 AM",
        "isVisible": true,
        "questions": [
            {
                "text": "1",
                "points": 10,
                "type": "QRL"
            },
            {
                "text": "2",
                "points": 10,
                "type": "QRL"
            },
            {
                "text": "3",
                "points": 10,
                "type": "QRL"
            },
            {
                "text": "Last",
                "points": 10,
                "type": "QRL"
            }
        ]
    }
]